packaage/__init__.py
packaage/aws.py
packaage/life.py
packaage/nlp.py
packaage/setup.py
packaage/test.py
packaage-0.0.8.dist-info/LICENSE.txt
packaage-0.0.8.dist-info/METADATA
packaage-0.0.8.dist-info/WHEEL
packaage-0.0.8.dist-info/top_level.txt
packaage-0.0.8.dist-info/RECORD
