Metadata-Version: 2.1
Name: packaage
Version: 0.0.8
Summary: Packaage is a Python library with few AI utils
License-File: LICENSE.txt
Requires-Dist: unidecode
Requires-Dist: boto3
Requires-Dist: psycopg2-binary
